<problem display_name="Quiz 1" markdown="null" weight="0.0">
  <p>Soient \(A\in M_{3\times 2}(\mathbb{R})\) et \(b\in M_{3\times 1}(\mathbb{R})\) la matrice est le vecteur colonne définis par \[A=\begin{pmatrix} 3 &amp; -6 \cr 4 &amp; -8 \cr 0 &amp; 1\end{pmatrix},~b=\begin{pmatrix} -1\cr7 \cr 2\end{pmatrix}.\]</p>
  <p> Les colonnes de \(A\) étant clairement indépendantes, il est possible de trouver une décomposition \(QR\) de cette matrice.</p>
  <p><b>Vrai ou Faux : </b> le système \(AX=b\) admet une unique solution au sens des moindres carrés, donnée par \(\hat{X}=(5,2)^T\).</p>
  <script type="text/python" system_path="python_lib">
def hint_fn(answer_ids, student_answers, new_cmap, old_cmap):
  aid = answer_ids[0]
  ans = ''
  feedback = ''
  correctness = False
  if not student_answers:
  	feedback = 'Veuillez s\'il-vous-plaît cocher une possibilité.'
  else:
    ans = str(student_answers[aid]).lower()
  print 'hint_fn called, ans=', ans
  if 'choice_1' in ans:
    feedback = 'C\'est incorrect. En effet, d\'après le résultat vu en cours, l\'unique solution du système \(AX=b\) au sens des moindres carrés est donnée par \[\hat{X}=R^{-1}Q^Tb,\] où \(A=QR\). On pourra s\'aider de la décomposition \(QR\) de \(A\) précédemment calculée dans le quiz 1 de la section précédente (9.13). ' 
  elif 'choice_0' in ans:
    feedback = 'Correct! En effet, on rappelle (voir Quiz 1, section 9.13) qu\'une factorisation \(QR\) de \(A\) est donnée par \[A=QR=\\begin{pmatrix}\\tfrac{3}{5}&amp; 0 \cr \\tfrac{4}{5} &amp; 0 \cr 0 &amp;1\\end{pmatrix}  \\begin{pmatrix} 5&amp; -10 \cr 0 &amp; 1\\end{pmatrix}.\] Ainsi, d\'après le résultat vu en cours, l\'unique solution du système \(AX=b\) au sens des moindres carrés est donnée par \[\hat{X}=R^{-1}Q^Tb=\\begin{pmatrix}\\tfrac{1}{5} &amp; 2 \cr 0 &amp; 1\\end{pmatrix} \\begin{pmatrix}\\tfrac{3}{5} &amp; \\tfrac{4}{5} &amp; 0 \cr 0 &amp; 0 &amp; 1 \\end{pmatrix} \\begin{pmatrix} -1\cr7 \cr 2\\end{pmatrix} = \\begin{pmatrix}\\tfrac{1}{5} &amp; 2 \cr 0 &amp; 1\\end{pmatrix} \\begin{pmatrix} 5 \cr 2 \\end{pmatrix}=\\begin{pmatrix} 5 \cr 2 \\end{pmatrix}.\] '
    correctness = True
  if feedback:
    if correctness is True:
      feedback = "&lt;font color='green'&gt;{0}&lt;/font&gt;".format(feedback)
    else:
      feedback = "&lt;font color='red'&gt;{0}&lt;/font&gt;".format(feedback)
    new_cmap.set_hint_and_mode(aid,feedback,'always')
</script>
  <multiplechoiceresponse>
    <choicegroup type="MultipleChoice">
      <choice correct="true"> Vrai.</choice>
      <choice correct="false">Faux.</choice>
    </choicegroup>
    <hintgroup hintfn="hint_fn"/>
  </multiplechoiceresponse>
</problem>
